htsmodels/__init__.py
htsmodels/Tests/__init__.py
htsmodels/Tests/test_deepar_missing_values.py
htsmodels/Tests/test_deepar_results.py
htsmodels/Tests/test_deepvar_results.py
htsmodels/Tests/test_mint_missing_values.py
htsmodels/Tests/test_mint_missing_values_tourism.py
htsmodels/Tests/test_mint_results_m5.py
htsmodels/Tests/test_mint_results_police.py
htsmodels/Tests/test_mint_results_store_prison.py
htsmodels/Tests/test_mint_results_tourism.py
htsmodels/Tests/test_standard_gp_prison.py
htsmodels/Tests/test_tft_results.py
htsmodels/models/__init__.py
htsmodels/models/gluon_models.py
htsmodels/models/gp.py
htsmodels/models/mean_functions.py
htsmodels/models/mint.py
htsmodels/models/standard_gp.py
htsmodels/preprocessing/__init__.py
htsmodels/preprocessing/subsampled_dataset.py
htsmodels/results/__init__.py
htsmodels/results/calculate_metrics.py
htsmodels/utils/__init__.py
htsmodels/utils/logger.py
htsmodels-0.3.28.dist-info/METADATA
htsmodels-0.3.28.dist-info/WHEEL
htsmodels-0.3.28.dist-info/top_level.txt
htsmodels-0.3.28.dist-info/RECORD
