Metadata-Version: 2.1
Name: htsmodels
Version: 0.3.28
Summary: Forecasting algorithms for hierarchical time series
Home-page: UNKNOWN
Author: Luis Roque
Author-email: <roque0luis@gmail.com>
License: UNKNOWN
Keywords: python,time series,hierarchical,forecasting,htsmodels,machine learning
Platform: UNKNOWN
Classifier: Development Status :: 2 - Pre-Alpha
Classifier: Intended Audience :: Science/Research
Classifier: Topic :: Scientific/Engineering
Classifier: Programming Language :: Python :: 3
Classifier: Operating System :: OS Independent
Requires-Dist: setuptools ~=58.0.4
Requires-Dist: tsaugmentation ~=0.5.26
Requires-Dist: pandas ~=1.2.5
Requires-Dist: rpy2 ~=3.4.5
Requires-Dist: numpy ~=1.23.5
Requires-Dist: gluonts ~=0.11.2
Requires-Dist: tqdm ~=4.62.3
Requires-Dist: scikit-learn ~=1.0.1
Requires-Dist: mxnet ~=1.8.0
Requires-Dist: gpytorch ~=1.9.0
Requires-Dist: torch ~=2.0.1
